hqtools/__init__.py
hqtools/log.py
hqtools/mongodb.py
hqtools-0.0.1.dist-info/LICENSE
hqtools-0.0.1.dist-info/METADATA
hqtools-0.0.1.dist-info/WHEEL
hqtools-0.0.1.dist-info/top_level.txt
hqtools-0.0.1.dist-info/RECORD
